{"acrossmap":null,"admin":false,"answers":{"across":["SLEEPOVER","WAFTS","PUNCHLINE","AGORA","ECTODERMS","STRAM","EKE","SUITS","SHIP","DONOT","STAY","ILL","SUTTER","YRS","CREE","TETLEY","ETCHERS","ALDA","AERO","BULWARK","SMELLS","ONEA","EEE","SELENA","ANA","STUD","PATES","REVS","SYRIA","RES","DREAM","YORKSHIRE","EVITA","APTITUDES","RENEE","KEYNOTERS"],"down":["SPEEDS","LUCKOUT","ENTENTE","ECO","PHD","OLES","VIRUS","ENMITY","RESTAREAS","WAS","AGTS","FORHIRE","TRAILER","SAMPLES","SYSTEMS","OTTAWA","TELLA","REDRESS","CHOLLA","YAKETYYAK","CREEP","BOARDER","UNNERVE","LEAVEIN","LETRIDE","SNEERER","EUROPE","ASSESS","DIRTY","SATE","AKIN","MAE","STO","HUT"]},"author":"R. Norris","autowrap":null,"bbars":null,"circles":null,"clues":{"across":["1. Certain party","10. Floats","15. End of a routine","16. Mall forerunner","17. Embryological layers","18. Former Chiefs' coach Hank","19. Squeeze (out)","20. Businessmen, slangily","22. Send","23. Words of warning","26. Postponement","27. Unfavorably","28. John ___, California gold rush figure","30. Calendar periods: Abbr.","31. Manitoba native","32. Lipton alternative","34. Some artists","36. \"Crimes and Misdemeanors\" actor","37. Prefix with space","38. Mainstay","41. Is suspicious","44. Most eligible, once","45. AAA's opposite?","47. Late Mexican-American vocalist","49. Alicia of \"Falcon Crest\"","50. Poker choice","52. Some spreads","53. Guns","55. Al-Assad's land","57. Abbr. next to a telephone number","58. Fancy","60. Hog with erect ears","63. Madonna role","64. Talents","65. \"Walk Away ___\" (1966 hit)","66. Convention figures"],"down":["1. Zips","2. Get a break","3. Triple ___","4. \"Green\": Prefix","5. Scholar's goal","6. Motivation for Manolete","7. Bug","8. Rancor","9. Turnpike locales","10. Used to be","11. Govt. employees","12. Available","13. Kind of park","14. Salesman's load","21. Kind of analysis","24. Capital on the Rideau Canal","25. \"I cannot ___ lie\"","29. Satisfaction","31. Spiny cactus","33. 1958 #1 song","35. Undesirable","38. Transient","39. Shake up","40. Do not delete","42. Not make an issue of","43. Villain, at times","46. Land on the Mediterranean","48. Size up","51. Epithet for Harry Callahan","54. Fill","56. Similar","59. Pearl Bailey's middle name","61. I stand: Lat.","62. Shack"]},"code":null,"copyright":"1997, The New York Times","date":"2\/7\/1997","dow":"Friday","downmap":null,"editor":"W. Shortz","grid":["S","L","E","E","P","O","V","E","R",".","W","A","F","T","S","P","U","N","C","H","L","I","N","E",".","A","G","O","R","A","E","C","T","O","D","E","R","M","S",".","S","T","R","A","M","E","K","E",".",".","S","U","I","T","S",".","S","H","I","P","D","O","N","O","T",".","S","T","A","Y",".",".","I","L","L","S","U","T","T","E","R",".","Y","R","S",".","C","R","E","E",".","T","E","T","L","E","Y",".","E","T","C","H","E","R","S",".",".",".","A","L","D","A",".","A","E","R","O",".",".",".","B","U","L","W","A","R","K",".","S","M","E","L","L","S",".","O","N","E","A",".","E","E","E",".","S","E","L","E","N","A","A","N","A",".",".","S","T","U","D",".","P","A","T","E","S","R","E","V","S",".","S","Y","R","I","A",".",".","R","E","S","D","R","E","A","M",".","Y","O","R","K","S","H","I","R","E","E","V","I","T","A",".","A","P","T","I","T","U","D","E","S","R","E","N","E","E",".","K","E","Y","N","O","T","E","R","S"],"gridnums":[1,2,3,4,5,6,7,8,9,0,10,11,12,13,14,15,0,0,0,0,0,0,0,0,0,16,0,0,0,0,17,0,0,0,0,0,0,0,0,0,18,0,0,0,0,19,0,0,0,0,20,0,0,0,21,0,22,0,0,0,23,0,0,24,25,0,26,0,0,0,0,0,27,0,0,28,0,0,0,0,29,0,30,0,0,0,31,0,0,0,0,32,0,0,0,0,33,0,34,0,35,0,0,0,0,0,0,0,36,0,0,0,0,37,0,0,0,0,0,0,38,39,40,0,0,0,0,0,41,0,0,0,42,43,0,44,0,0,0,0,45,0,46,0,47,0,0,0,0,48,49,0,0,0,0,50,0,0,51,0,52,0,0,0,0,53,0,0,54,0,55,0,0,0,56,0,0,57,0,0,58,0,0,0,59,0,60,0,0,0,61,62,0,0,0,63,0,0,0,0,0,64,0,0,0,0,0,0,0,0,65,0,0,0,0,0,66,0,0,0,0,0,0,0,0],"hold":null,"id":null,"id2":null,"interpretcolors":null,"jnotes":null,"key":null,"mini":null,"notepad":null,"publisher":"The New York Times","rbars":null,"shadecircles":null,"size":{"cols":15,"rows":15},"title":"NY TIMES, FRI, FEB 07, 1997","track":null,"type":null}