{"acrossmap":null,"admin":false,"answers":{"across":["PROS","ARC","FBI","POLES","PULP","IRON","STERE","SEAL","DESK","COVEREDWAGONS","IDES","TALC","ANGLES","FETISHES","DARED","CUPEL","CAT","ACE","BONER","USO","PRY","CRANE","SAFER","TEMERITY","BARFLY","AMOS","SALE","STOCKEXCHANGE","WATT","EVER","MOUTH","OGEE","TINE","ISLES","EAR","LOW","ELSE"],"down":["PPS","ROTC","OLEO","SERVILE","APSES","RUED","CLAW","FRENCHCUFF","BOSS","INK","SEEDED","PLATTER","IDOLS","RES","GAIL","ADAPT","NACRE","GREYMATTER","FUNNY","EPEE","EASEL","STORY","COAT","BRISKET","CROC","SALAMI","ARENOSE","EMOTE","BAH","SCREW","SAGA","EVIL","XENO","GULL","ETES","WOE","HSE"]},"author":"Brian G. Tyler","autowrap":null,"bbars":null,"circles":null,"clues":{"across":["1. Golf-tour players","5. Curve part","8. Govt. agency","11. North and South","13. Juice-glass residue","15. Pressing necessity","16. Metric measure","17. Fasten","18. Secretary","19. Insured vehicles","22. March 15","23. Powdery mineral","24. Right and obtuse","27. Fixations","31. Provoked","32. Assayer's vessel","33. Persian or alley","34. Good hole card","35. Blunder","36. G.I. org.","37. Meddle","38. Construction-site sight","39. Less dangerous","41. Rashness","43. Alcoholic insect, perhaps","44. Andy's partner","45. Fire or garage event","46. Cattle trade","51. Inventor James","52. Constantly","53. Utter pompously","55. Molding","56. Fork part","57. British and others","58. Head part","59. Cattle sound","60. Or ___"],"down":["1. Letter adjunct: Abbr.","2. Campus org.","3. Spread","4. Obsequious","5. Church parts","6. Regretted","7. Talon","8. Slap, in Paris","9. Domineer","10. India, for one","12. Did a lawn job","14. Silver item","15. Star athletes, to children","20. In medias ___","21. Appropriate name for a hurricane","24. Adjust","25. Mother-of-pearl","26. Thing involving Zane or Lady Jane","27. Girl or bone","28. Sword","29. Canvas support","30. Tall or short","32. Paint layer","35. Meat cut","38. Nile swimmer, for short","39. Deli offering","40. Sandy","42. Act the ham","43. Scrooge word","45. Something often loose","46. Forsyte, for one","47. Vile","48. Strange: Prefix","49. Hoodwink","50. French seasons","51. Grief","54. Congress unit: Abbr."]},"code":null,"copyright":"1976, The New York Times","date":"1\/9\/1976","dow":"Friday","downmap":null,"editor":"Will Weng","grid":["P","R","O","S",".",".","A","R","C",".",".",".","F","B","I","P","O","L","E","S",".","P","U","L","P",".","I","R","O","N","S","T","E","R","E",".","S","E","A","L",".","D","E","S","K",".","C","O","V","E","R","E","D","W","A","G","O","N","S",".",".",".",".","I","D","E","S",".",".","T","A","L","C",".",".","A","N","G","L","E","S",".","F","E","T","I","S","H","E","S","D","A","R","E","D",".","C","U","P","E","L",".","C","A","T","A","C","E",".",".","B","O","N","E","R",".",".","U","S","O","P","R","Y",".","C","R","A","N","E",".","S","A","F","E","R","T","E","M","E","R","I","T","Y",".","B","A","R","F","L","Y",".",".","A","M","O","S",".",".","S","A","L","E",".",".",".",".","S","T","O","C","K","E","X","C","H","A","N","G","E",".","W","A","T","T",".","E","V","E","R",".","M","O","U","T","H","O","G","E","E",".","T","I","N","E",".","I","S","L","E","S","E","A","R",".",".",".","L","O","W",".",".","E","L","S","E"],"gridnums":[1,2,3,4,0,0,5,6,7,0,0,0,8,9,10,11,0,0,0,12,0,13,0,0,14,0,15,0,0,0,16,0,0,0,0,0,17,0,0,0,0,18,0,0,0,0,19,0,0,0,20,0,0,0,0,21,0,0,0,0,0,0,0,22,0,0,0,0,0,23,0,0,0,0,0,24,25,26,0,0,0,0,27,28,0,0,0,0,29,30,31,0,0,0,0,0,32,0,0,0,0,0,33,0,0,34,0,0,0,0,35,0,0,0,0,0,0,36,0,0,37,0,0,0,38,0,0,0,0,0,39,40,0,0,0,41,0,0,42,0,0,0,0,0,43,0,0,0,0,0,0,0,44,0,0,0,0,0,45,0,0,0,0,0,0,0,46,0,0,0,0,47,48,0,0,0,0,49,50,0,51,0,0,0,0,52,0,0,0,0,53,0,0,0,54,55,0,0,0,0,56,0,0,0,0,57,0,0,0,0,58,0,0,0,0,0,59,0,0,0,0,60,0,0,0],"hold":null,"id":null,"id2":null,"interpretcolors":null,"jnotes":null,"key":null,"mini":null,"notepad":null,"publisher":"The New York Times","rbars":null,"shadecircles":null,"size":{"cols":15,"rows":15},"title":"NY TIMES, FRI, JAN 09, 1976","track":null,"type":null}