{"acrossmap":null,"admin":false,"answers":{"across":["ASPEN","DALI","AMID","THESE","EGAN","VIVA","TASTE","MOTS","ELAN","GOODNIGHTIRENE","PLO","SEC","PAR","ELKE","PIECES","ORAL","AILS","ERODE","LOVEANDMARRIAGE","EMEND","SEMI","STEM","SANDAL","REST","IRS","GAL","EON","ILLBESEEINGYOU","NEAR","TERN","GLARE","KATE","ERIN","LORDS","SKEW","DYES","ENSUE"],"down":["ATT","SHAG","PESO","ESTOP","NEEDLE","DEMI","AGOG","LATHS","INSTEP","AVER","MILE","IVAN","DANE","NOLAN","ICIER","POLES","AROMA","RAVEN","KIDS","ELMER","ERIS","COATI","EDGER","SEEMS","LEND","SAME","ADAGE","RISEN","LASTED","TOGGLE","LEERY","NYLON","INKS","LEAK","LATE","BREW","ERIE","INNS","OARS","URDU","ESE"]},"author":"Albert J. Klaus","autowrap":null,"bbars":null,"circles":null,"clues":{"across":["1. John Denver's \"Christmas in _____\"","6. \"Tuna-Fishing\" painter","10. Among","14. \"_____ Eyes\" (1969 song)","15. Actor Richard","16. Bounty rival","17. Refinement","18. Witticisms","19. Vigor","20. 1950 Sinatra hit","23. West Bank org.","24. \"Just a _____\"","25. Three strokes, perhaps","28. Actress Sommer","31. Shares","36. Feared test","38. Troubles","40. Weaken","41. 1955 Sinatra hit","44. Improve","45. Rig","46. Shut off","47. Beachwear","49. Relax","51. Audit conductor, for short","52. Guy's date","54. Eternity","56. 1961 Sinatra hit","64. \"Warm\"","65. Minnow eater","66. Driving hazard","68. Petruchio's mate","69. Shillelagh land","70. 10th-day-of- Christmas gift","71. Swerve","72. Henna and others","73. Follow"],"down":["1. Blue-chip symbol","2. Lively dance","3. Chihuahua change","4. Bar, in law","5. Compass part","6. Half begun?","7. Excited","8. Stucco backing","9. Foot part","10. Swear","11. Ryun's run","12. Basil's successor","13. Niels Bohr, e.g.","21. The Man Without a Country","22. More aloof","25. Propels a gondola","26. Bouquet","27. Bird \"perched upon a bust of Pallas\"","29. Toddlers","30. Dramatist Rice","32. Goddess of discord","33. Raccoon kin","34. Lawn tool","35. Is apparent","37. Impart","39. Ditto","42. Saw","43. Elevated","48. Stood up","50. Kind of switch","53. Distrustful","55. Run site","56. Prepares the presses","57. Plumber's concern","58. Behind","59. Ale","60. Pennsylvania port","61. Roadhouses","62. They go into locks","63. Relative of Hindustani","67. Volte-face WNW"]},"code":null,"copyright":"1994, The New York Times","date":"1\/11\/1994","dow":"Tuesday","downmap":null,"editor":"Will Shortz","grid":["A","S","P","E","N",".","D","A","L","I",".","A","M","I","D","T","H","E","S","E",".","E","G","A","N",".","V","I","V","A","T","A","S","T","E",".","M","O","T","S",".","E","L","A","N",".","G","O","O","D","N","I","G","H","T","I","R","E","N","E",".",".",".","P","L","O",".",".","S","E","C",".",".",".",".","P","A","R",".","E","L","K","E",".","P","I","E","C","E","S","O","R","A","L",".","A","I","L","S",".","E","R","O","D","E","L","O","V","E","A","N","D","M","A","R","R","I","A","G","E","E","M","E","N","D",".","S","E","M","I",".","S","T","E","M","S","A","N","D","A","L",".","R","E","S","T",".","I","R","S",".",".",".",".","G","A","L",".",".","E","O","N",".",".",".","I","L","L","B","E","S","E","E","I","N","G","Y","O","U",".","N","E","A","R",".","T","E","R","N",".","G","L","A","R","E","K","A","T","E",".","E","R","I","N",".","L","O","R","D","S","S","K","E","W",".","D","Y","E","S",".","E","N","S","U","E"],"gridnums":[1,2,3,4,5,0,6,7,8,9,0,10,11,12,13,14,0,0,0,0,0,15,0,0,0,0,16,0,0,0,17,0,0,0,0,0,18,0,0,0,0,19,0,0,0,0,20,0,0,0,21,0,0,0,0,22,0,0,0,0,0,0,0,23,0,0,0,0,24,0,0,0,0,0,0,25,26,27,0,28,0,29,30,0,31,0,32,33,34,35,36,0,0,37,0,38,0,0,39,0,40,0,0,0,0,41,0,0,0,42,0,0,0,0,43,0,0,0,0,0,44,0,0,0,0,0,45,0,0,0,0,46,0,0,0,47,0,0,0,0,48,0,49,0,0,50,0,51,0,0,0,0,0,0,52,0,53,0,0,54,0,55,0,0,0,56,57,58,59,0,0,0,60,61,0,0,0,62,63,0,64,0,0,0,0,65,0,0,0,0,66,0,0,0,67,68,0,0,0,0,69,0,0,0,0,70,0,0,0,0,71,0,0,0,0,72,0,0,0,0,73,0,0,0,0],"hold":null,"id":null,"id2":null,"interpretcolors":null,"jnotes":null,"key":null,"mini":null,"notepad":null,"publisher":"The New York Times","rbars":null,"shadecircles":null,"size":{"cols":15,"rows":15},"title":"NY TIMES, TUESDAY, JANUARY 11, 1994","track":null,"type":null}