{"acrossmap":null,"admin":false,"answers":{"across":["CRISES","APPOSES","RECENT","UNLEARNT","ITASCA","NAILFILE","MORTAR","CLEF","LAP","PRIESTHOOD","GARP","STATESONG","TINGE","MOOS","CONKED","TOREUPTHEROAD","SONANT","REAP","EBERT","FALSECARD","METE","BOILEDOVER","ISH","MORN","LONELY","NUISANCE","ENGRAM","ARRANGED","SEESTO","REDWOOD","STREEP"],"down":["CRIMPS","RETORT","ICARIA","SESTET","ENCASEMENT","STARTSOUT","ANALOG","PLIED","PELF","OAF","SRILANKA","ENLARGED","STEPPED","UNCONSTRAINED","HOOP","GINO","TORPEDONET","CEASELESS","TOBESURE","ONETHIRD","RARE","HELL","SEMINAR","FORCED","CONGER","AVERSE","RELATE","DRYMOP","BONGO","MANO","SAW"]},"author":"Patrick Berry","autowrap":null,"bbars":null,"circles":null,"clues":{"across":["1. Dramatic situations","7. Places side by side","14. Fresh","15. Like discarded habits","16. Lake ___, source of the Mississippi","17. It can take the edge off","18. Hod filler","19. One that heads up the staff","20. Baby seat, say","21. White-collar profession?","23. Irving hero","24. \"Missouri Waltz,\" e.g.","25. Smattering","26. Cattle calls","27. Rendered unconscious, maybe","28. Burned rubber","32. Voiced","33. Take in","34. Famous Chicago critic","35. Lead to mislead, in bridge","40. Hand (out)","41. Blew up","42. Meeting time suffix","43. In \"Hamlet,\" it's \"in russet mantle clad\"","44. Unfrequented","45. Harrier","47. Memory trace","48. Set","49. Looks after","50. California's ___ National Park","51. \"Death Becomes Her\" star, 1992"],"down":["1. Makes waves","2. Come back with","3. Failed utopian community of 1840's Illinois","4. Bard's work","5. Means of protecting breakables","6. Begins","7. Having hands, as a clock","8. Furnished (with)","9. Ill-gotten funds","10. Butterfingers","11. It means \"resplendent land\" in Sinhalese","12. Blew up","13. Like Mayan pyramids","15. At liberty","22. Cager's target","23. Italian painter Severini","25. Protection for a boat's hull","27. Nonstop","28. Admittedly","29. Four in every dozen","30. Choice","31. Something to catch or raise","32. Limited course","35. Unnatural","36. Certain eel","37. Not sympathetic","38. Pertain","39. Dust remover","41. Drum played without sticks","43. Rancho hand?","46. Bromide"]},"code":null,"copyright":"2003, The New York Times","date":"3\/8\/2003","dow":"Saturday","downmap":null,"editor":"Will Shortz","grid":["C","R","I","S","E","S",".",".","A","P","P","O","S","E","S","R","E","C","E","N","T",".","U","N","L","E","A","R","N","T","I","T","A","S","C","A",".","N","A","I","L","F","I","L","E","M","O","R","T","A","R",".","C","L","E","F",".","L","A","P","P","R","I","E","S","T","H","O","O","D",".","G","A","R","P","S","T","A","T","E","S","O","N","G",".","T","I","N","G","E",".",".",".",".","M","O","O","S",".","C","O","N","K","E","D",".","T","O","R","E","U","P","T","H","E","R","O","A","D",".","S","O","N","A","N","T",".","R","E","A","P",".",".",".",".","E","B","E","R","T",".","F","A","L","S","E","C","A","R","D","M","E","T","E",".","B","O","I","L","E","D","O","V","E","R","I","S","H",".","M","O","R","N",".","L","O","N","E","L","Y","N","U","I","S","A","N","C","E",".","E","N","G","R","A","M","A","R","R","A","N","G","E","D",".","S","E","E","S","T","O","R","E","D","W","O","O","D",".",".","S","T","R","E","E","P"],"gridnums":[1,2,3,4,5,6,0,0,7,8,9,10,11,12,13,14,0,0,0,0,0,0,15,0,0,0,0,0,0,0,16,0,0,0,0,0,0,17,0,0,0,0,0,0,0,18,0,0,0,0,0,0,19,0,0,0,0,20,0,0,21,0,0,0,0,0,22,0,0,0,0,23,0,0,0,24,0,0,0,0,0,0,0,0,0,25,0,0,0,0,0,0,0,0,26,0,0,0,0,27,0,0,0,0,0,0,28,29,30,0,0,0,0,31,0,0,0,0,0,0,32,0,0,0,0,0,0,33,0,0,0,0,0,0,0,34,0,0,0,0,0,35,0,0,0,0,36,37,38,39,40,0,0,0,0,41,0,0,0,0,0,0,0,0,0,42,0,0,0,43,0,0,0,0,44,0,0,0,0,0,45,0,0,46,0,0,0,0,0,47,0,0,0,0,0,48,0,0,0,0,0,0,0,0,49,0,0,0,0,0,50,0,0,0,0,0,0,0,0,51,0,0,0,0,0],"hold":null,"id":null,"id2":null,"interpretcolors":null,"jnotes":null,"key":null,"mini":null,"notepad":null,"publisher":"The New York Times","rbars":null,"shadecircles":null,"size":{"cols":15,"rows":15},"title":"NY TIMES, SAT, MAR 08, 2003","track":null,"type":null}