{"acrossmap":null,"admin":false,"answers":{"across":["BEAM","DIOR","JESSE","ALFA","ETNA","OZAWA","HARDYBOYSSERIES","SNOCAT","XCI","ALEE","ALOE","ALF","HARPERVALLEYPTA","ALI","SIL","SEERED","ROSIE","LOS","DRANO","SHERRI","NAP","DEB","HARVARDGRADUATE","TAR","ISON","ETTU","QUA","TIPTOP","LAUGHINGOUTLOUD","KUBLA","KERR","URSA","STAYS","SERE","GETS"],"down":["BAHS","ELAN","AFRO","MADCAP","DEBTORS","ITO","ONYX","RASCAL","JOE","EZRA","SAIL","SWEE","EASE","YALE","SILLS","EVIL","FEED","HARSH","ALOHA","RISER","ALONG","YER","PRADA","TENET","ADOBE","IRV","ERAT","SARI","IRAQI","PASTURE","DRUNKS","DOIT","UNPLUG","ELKS","TAUT","TUBA","UGLY","AGEE","TORE","OUST","PDAS","HAS","ORR"]},"author":"Andrea Carla Michaels","autowrap":null,"bbars":null,"circles":null,"clues":{"across":["1. Smile broadly","5. Fashion designer Christian","9. Outlaw ___ James","14. ___ Romeo (Italian car)","15. Sicilian peak","16. Seiji ___, former Boston Symphony director","17. Mysteries starting with \"The Tower Treasure\" and \"The House on the Cliff\"","20. Ski resort vehicle","21. 91, to Nero","22. Sheltered at sea","23. Soothing stuff","25. Furry TV extraterrestrial","27. 1968 hit song that spawned a 1978 movie and a 1981 TV show","35. \"Float like a butterfly, sting like a bee\" boxer","36. \"Répondez ___ vous plaît\"","37. Become enraged","38. Comedian\/TV host once called the \"Queen of Nice\"","41. The \"L\" of U.C.L.A.","43. Liquid-Plumr rival","44. \"The View\" co-host ___ Shepherd","46. Forty winks","48. Belle of the ball, for short","49. Crimson alumnus","53. Driveway topper","54. \"Help ___ the way!\"","55. Accusation to Brutus","59. Sine ___ non","61. Acme","65. Bit of textspeak, unshortened ... or a hint to the starts of 17-, 27- and 49-Across","68. Coleridge's \"___ Khan\"","69. Deborah who was nominated for a record six Best Actress Oscars without ever winning","70. Bear in constellation names","71. Death row reprieves","72. Very dry","73. Comprehends"],"down":["1. Exclamations from Scrooge","2. Pizazz","3. Retro hairstyle","4. Wild and crazy","5. Ones owing money","6. \"Who am ___ judge?\"","7. Jet-black gem","8. Little troublemaker","9. Baseball's DiMaggio","10. Biblical prophet","11. Go wherever the wind blows?","12. ___'Pea (Popeye's kid)","13. Military order, after \"at\"","18. Where Bill and Hillary Clinton met","19. Window ledges","24. Wicked","26. Oats, for a horse","27. Like Siberian winters","28. 2015 rom-com set in Hawaii","29. Staircase part","30. \"I knew it all ___!\"","31. \"So's ___ old man!\"","32. Gucci alternative","33. Founding principle","34. Pueblo brick","39. ___ Cross, first African-American full-time sports analyst on national TV","40. The \"E\" of Q.E.D.","42. Hindu dress","45. Baghdad native","47. Grazing land","50. Sots","51. \"Just ___\" (Nike slogan)","52. Go acoustic, informally","55. Antlered animals","56. Like a rope during a tug-of-war match","57. Marching band instrument","58. Hideous","60. \"A Death in the Family\" writer James","62. Shredded","63. Remove, as in a coup","64. Multipurpose hand-held devices, for short","66. \"Elvis ___ left the building\"","67. Bobby of the N.H.L."]},"code":null,"copyright":"2015, The New York Times","date":"8\/17\/2015","dow":"Monday","downmap":null,"editor":"Will Shortz","grid":["B","E","A","M",".","D","I","O","R",".","J","E","S","S","E","A","L","F","A",".","E","T","N","A",".","O","Z","A","W","A","H","A","R","D","Y","B","O","Y","S","S","E","R","I","E","S","S","N","O","C","A","T",".","X","C","I",".","A","L","E","E",".",".",".","A","L","O","E",".","A","L","F",".",".",".",".","H","A","R","P","E","R","V","A","L","L","E","Y","P","T","A","A","L","I",".",".","S","I","L",".","S","E","E","R","E","D","R","O","S","I","E",".","L","O","S",".","D","R","A","N","O","S","H","E","R","R","I",".","N","A","P",".",".","D","E","B","H","A","R","V","A","R","D","G","R","A","D","U","A","T","E",".",".",".",".","T","A","R",".","I","S","O","N",".",".",".","E","T","T","U",".","Q","U","A",".","T","I","P","T","O","P","L","A","U","G","H","I","N","G","O","U","T","L","O","U","D","K","U","B","L","A",".","K","E","R","R",".","U","R","S","A","S","T","A","Y","S",".","S","E","R","E",".","G","E","T","S"],"gridnums":[1,2,3,4,0,5,6,7,8,0,9,10,11,12,13,14,0,0,0,0,15,0,0,0,0,16,0,0,0,0,17,0,0,0,18,0,0,0,0,19,0,0,0,0,0,20,0,0,0,0,0,0,21,0,0,0,22,0,0,0,0,0,0,23,0,0,24,0,25,0,26,0,0,0,0,27,28,29,0,0,0,0,30,0,0,0,31,32,33,34,35,0,0,0,0,36,0,0,0,37,0,0,0,0,0,38,0,0,39,40,0,41,0,42,0,43,0,0,0,0,44,0,0,0,0,45,0,46,0,47,0,0,48,0,0,49,0,0,0,0,0,50,0,0,0,51,52,0,0,0,0,0,0,0,53,0,0,0,54,0,0,0,0,0,0,55,56,57,58,0,59,0,60,0,61,0,0,62,63,64,65,0,0,0,66,0,0,0,67,0,0,0,0,0,0,68,0,0,0,0,0,69,0,0,0,0,70,0,0,0,71,0,0,0,0,0,72,0,0,0,0,73,0,0,0],"hastitle":false,"hold":null,"id":null,"id2":null,"interpretcolors":null,"jnotes":null,"key":null,"mini":null,"notepad":null,"publisher":"The New York Times","rbars":null,"shadecircles":null,"size":{"cols":15,"rows":15},"title":"NY TIMES, MON, AUG 17, 2015","track":null,"type":null,"uniclue":false}