{"acrossmap":null,"admin":false,"answers":{"across":["BAGS","SKIRT","ABAB","AILS","LINER","BONA","STATUEOFLIBERTY","ICC","NEW","BULGES","SHEASTADIUM","CAY","ERNS","NIL","FERRY","FLOE","COTY","ACHE","PEANS","ANON","TRES","RIIS","BRONX","SUA","SIGN","LAO","CONEYISLAND","CAESAR","EST","DUO","EMPIRESTATEBLDG","NEIL","SCARE","TEEM","EXCL","SHINN","URSA"],"down":["BASIS","AITCH","GLACE","SST","SLEETY","KIOWA","INF","REL","TRIBUNES","ABEL","BORG","ANTE","BAYS","UNSAY","BUMS","ACRES","DELAINE","IRONS","NONO","ITON","LYNX","FATS","ECRU","RHEA","FEIGN","CAROL","PRIORESS","BASTE","SCAR","LISTEN","YEARN","ADLER","NUDES","DOGMA","CENE","AMEX","EPIC","SILL","SCH","TAI","BTU"]},"author":"William Jarvis","autowrap":null,"bbars":null,"circles":null,"clues":{"across":["1. Captures","5. Avoid out of fear","10. Rhyme scheme","14. Troubles","15. Ship or plane","16. ___ fide","17. New York's \"French connection\"","20. Fed. rate-fixing agency","21. Word with England or York","22. Inverted dents","23. Site of the \"Miracle of '69\"","27. Coral island","28. Sea eagles","29. Zilch","32. Staten Island ___","35. Ice mass","36. President of France: 1954–59","37. Tooth or head follower","38. Songs of praise: Var.","39. Prolific author","40. French intensive","41. Author of \"Out of Mulberry Street\"","42. Site of a famous zoo","43. \"Apologia pro Vita ___\": Newman","44. Shingle","45. Thai language","46. Brooklyn's answer to the Riviera","51. \"Render therefore unto ___ . . . \"","55. Time zone abbr.","56. Batman and Robin","57. Hangout for Kong","61. Astronaut Armstrong","62. What ogres do","63. Abound","64. Opposite of incl.","65. Everett ___, \"ashcan realist\"","66. ___ Major"],"down":["1. Foundation","2. Gee trailer","3. Candied","4. Speedy airplane","5. Icy and rainy","6. Indians of the Southwest","7. Part of speech: Abbr.","8. Unit of electricity","9. Public defenders","10. Fourth person","11. Rival of Connors","12. Poker stake","13. Buzzards and Donegal","18. Recant","19. One-time pets of Brooklyn fans","24. Estate","25. Lightweight woolen fabric","26. Clubs used at Westchester","29. Advice to Nanette","30. Take ___ the lam","31. Kind of wildcat","32. Domino or Waller","33. Beige","34. Ostrich's look-alike","35. Pretend","36. Burnett or Channing","38. Chaucer character","42. Sew loosely or thrash","44. Cicatrix","45. First word of Longfellow's poem on Revere","47. Pine","48. Larry ___, famed harmonica player","49. Many paintings by Renoir","50. Thomas Aquinas' specialty","51. Geologic comb. form","52. Second-largest U.S. stock exchange","53. \"Iliad\" or \"Odyssey\"","54. Part of a window","58. Acad.","59. Asian people","60. Quant. of heat"]},"code":null,"copyright":"1979, The New York Times","date":"5\/8\/1979","dow":"Tuesday","downmap":null,"editor":"Eugene T. Maleska","grid":["B","A","G","S",".","S","K","I","R","T",".","A","B","A","B","A","I","L","S",".","L","I","N","E","R",".","B","O","N","A","S","T","A","T","U","E","O","F","L","I","B","E","R","T","Y","I","C","C",".","N","E","W",".",".","B","U","L","G","E","S","S","H","E","A","S","T","A","D","I","U","M",".",".",".",".",".",".",".","C","A","Y",".","E","R","N","S",".","N","I","L","F","E","R","R","Y",".","F","L","O","E",".","C","O","T","Y","A","C","H","E",".","P","E","A","N","S",".","A","N","O","N","T","R","E","S",".","R","I","I","S",".","B","R","O","N","X","S","U","A",".","S","I","G","N",".","L","A","O",".",".",".",".",".",".",".","C","O","N","E","Y","I","S","L","A","N","D","C","A","E","S","A","R",".",".","E","S","T",".","D","U","O","E","M","P","I","R","E","S","T","A","T","E","B","L","D","G","N","E","I","L",".","S","C","A","R","E",".","T","E","E","M","E","X","C","L",".","S","H","I","N","N",".","U","R","S","A"],"gridnums":[1,2,3,4,0,5,6,7,8,9,0,10,11,12,13,14,0,0,0,0,15,0,0,0,0,0,16,0,0,0,17,0,0,0,18,0,0,0,0,0,19,0,0,0,0,20,0,0,0,21,0,0,0,0,22,0,0,0,0,0,23,0,0,24,0,0,0,25,26,0,0,0,0,0,0,0,0,0,27,0,0,0,28,0,0,0,0,29,30,31,32,33,34,0,0,0,35,0,0,0,0,36,0,0,0,37,0,0,0,0,38,0,0,0,0,0,39,0,0,0,40,0,0,0,0,41,0,0,0,0,42,0,0,0,0,43,0,0,0,44,0,0,0,0,45,0,0,0,0,0,0,0,0,0,46,0,0,0,47,0,0,0,48,49,50,51,52,53,54,0,0,0,0,55,0,0,0,56,0,0,57,0,0,0,0,0,58,59,0,0,0,60,0,0,0,61,0,0,0,0,62,0,0,0,0,0,63,0,0,0,64,0,0,0,0,65,0,0,0,0,0,66,0,0,0],"hold":null,"id":null,"id2":null,"interpretcolors":null,"jnotes":null,"key":null,"mini":null,"notepad":null,"publisher":"The New York Times","rbars":null,"shadecircles":null,"size":{"cols":15,"rows":15},"title":"NY TIMES, TUE, MAY 08, 1979","track":null,"type":null}