{"acrossmap":null,"admin":false,"answers":{"across":["FORTKNOX","ARCA","OVEREASY","AVOUCH","REVERSAL","BAMBOO","GREENAGE","SNAILS","OAR","EMMET","CYT","ELICIT","INGRATE","SLEEVE","ENTAILED","CYLINDERS","BESILENT","EDEMAS","USELESS","SESAME","RTE","ACTAS","SMA","GRINGO","STAGESET","LINEUP","COGITATE","ENTREE","AVERAGER","SOIR","PEDDLERS"],"down":["FORGOES","OVERALL","REVERIE","TREE","KERN","NASA","OSAGE","XYLEM","AVANTGARDE","ROMA","CUBICAL","ACOLYTE","ABSENTEES","HOSTED","MIND","CECIL","IVYLEAGUER","TELESCOPE","RISES","ENT","INST","BURGLE","ESTRINS","SEEINTO","MASSAGE","AMMETER","SEATERS","ASCAP","STOVE","NERI","AGED","GIRD","ETAL"]},"author":"Randolph Ross","autowrap":null,"bbars":null,"circles":null,"clues":{"across":["1. Goldfinger's target","9. Chest on the Spanish Main","13. Egg order","14. Guarantee","16. Change of mind","17. Source of shoots","18. Meadowlands","19. Hoddy-doddies","20. Crewman","21. Ant, in dialect","23. Cellular prefix","24. Extract","28. Sore winner","30. Magician's secret place","31. Necessitated","32. The 8 in V-8","34. \"Shh!\"","37. Tomato troubles","41. Sisyphean","42. Opening word","43. Address abbr.","44. Represent in person","47. Little of Scotland","48. Yank in the Yucatan","50. Props and scenery","54. Police presentation","55. Put on one's thinking cap","56. Means of admittance","57. Mean person","58. Paris newspaper France-_____","59. Sidewalk entrepreneurs"],"down":["1. Skips","2. In general","3. Mental vacation, so to speak","4. Clothes hanger","5. \"Show Boat\" composer","6. Endeavour initials","7. River to the Missouri","8. Plant circulatory system","9. Cutting-edge","10. Villa Borghese site","11. Like dice","12. Attendant","14. Election tippers, sometimes","15. Presided over","22. Care","25. Mr. Rhodes of Rhodesia","26. Eli, for one","27. Shorten","29. Surges","31. M.D. specialty","33. Think tank: Abbr.","34. Rob","35. Female hormones","36. Use X-ray vision","38. Rolfing","39. Current calculator","40. Ushers","45. Org. co-founded by Victor Herbert","46. Coal burner","49. Rodolfo _____, first Mexican astronaut","51. Hoary","52. Prepare for action","53. Library catalogue abbr."]},"code":null,"copyright":"1995, The New York Times","date":"1\/7\/1995","dow":"Saturday","downmap":null,"editor":"Will Shortz","grid":["F","O","R","T","K","N","O","X",".",".","A","R","C","A",".","O","V","E","R","E","A","S","Y",".","A","V","O","U","C","H","R","E","V","E","R","S","A","L",".","B","A","M","B","O","O","G","R","E","E","N","A","G","E",".","S","N","A","I","L","S","O","A","R",".",".",".","E","M","M","E","T",".","C","Y","T","E","L","I","C","I","T",".",".","I","N","G","R","A","T","E","S","L","E","E","V","E",".","E","N","T","A","I","L","E","D",".",".",".","C","Y","L","I","N","D","E","R","S",".",".",".","B","E","S","I","L","E","N","T",".","E","D","E","M","A","S","U","S","E","L","E","S","S",".",".","S","E","S","A","M","E","R","T","E",".","A","C","T","A","S",".",".",".","S","M","A","G","R","I","N","G","O",".","S","T","A","G","E","S","E","T","L","I","N","E","U","P",".","C","O","G","I","T","A","T","E","E","N","T","R","E","E",".","A","V","E","R","A","G","E","R",".","S","O","I","R",".",".","P","E","D","D","L","E","R","S"],"gridnums":[1,2,3,4,5,6,7,8,0,0,9,10,11,12,0,13,0,0,0,0,0,0,0,0,14,0,0,0,0,15,16,0,0,0,0,0,0,0,0,17,0,0,0,0,0,18,0,0,0,0,0,0,0,0,19,0,0,0,0,0,20,0,0,0,0,0,21,0,22,0,0,0,23,0,0,24,0,0,25,26,27,0,0,28,0,0,29,0,0,0,30,0,0,0,0,0,0,31,0,0,0,0,0,0,0,0,0,0,32,0,0,33,0,0,0,0,0,0,0,0,34,35,36,0,0,0,0,0,0,37,0,0,38,39,40,41,0,0,0,0,0,0,0,0,42,0,0,0,0,0,43,0,0,0,44,0,0,45,46,0,0,0,47,0,0,48,0,0,49,0,0,0,50,0,51,52,53,0,0,0,54,0,0,0,0,0,0,55,0,0,0,0,0,0,0,56,0,0,0,0,0,0,57,0,0,0,0,0,0,0,0,58,0,0,0,0,0,59,0,0,0,0,0,0,0],"hold":null,"id":null,"id2":null,"interpretcolors":null,"jnotes":null,"key":null,"mini":null,"notepad":null,"publisher":"The New York Times","rbars":null,"shadecircles":null,"size":{"cols":15,"rows":15},"title":"NEW YORK TIMES SAT, JAN 7, 1995","track":null,"type":null}