{"acrossmap":null,"admin":false,"answers":{"across":["LOANS","OHMS","NARC","OWNUP","LEAD","ALEE","LETTERDAYS","VEES","NYPD","SERBS","LOBSTER","SKELTON","ALOP","OSCAR","SKA","SELECT","HULAS","HOTCHILIPEPPERS","SOPOR","SEAGAL","OTB","PINTA","NAVE","HERRING","BLOODED","STEIN","CAAN","URAL","EYESPECIAL","RISE","GENE","AINGE","ESTS","OATS","MAKES"],"down":["LOL","OWE","ANT","NUT","SPENT","OLDPRO","HEAD","MAY","SDS","NAVEL","ALERTS","REEBOK","CESSNA","RYE","SERAPE","LASH","OLEO","BOLT","SPECS","SCUP","KALES","SHIRT","CHOPIN","TIPIN","SPANO","LONG","EGAD","RAVE","SLED","OHSURE","TETRIS","BREAST","ABASES","RILES","LAP","ONEAM","CENT","EGO","YEA","CIA","INK","AGE","LES"]},"author":"Kyle Mahowald","autowrap":null,"bbars":null,"circles":[0,0,0,0,0,0,0,0,0,0,0,0,0,0,0,0,0,0,0,0,0,0,0,0,0,0,0,0,0,0,0,0,0,0,0,0,0,0,0,0,0,0,0,0,0,0,0,0,0,0,0,0,0,0,0,0,0,0,0,0,0,0,0,0,0,0,1,0,0,0,0,0,0,0,0,0,0,0,0,0,0,0,0,0,0,0,0,0,0,0,0,0,0,0,0,0,0,0,0,0,0,0,0,0,0,0,0,0,0,0,0,0,0,0,1,0,0,0,0,0,0,0,0,0,0,0,0,0,0,0,0,0,0,0,0,0,0,0,0,0,0,0,0,0,0,0,0,0,0,0,0,0,0,0,0,0,0,0,0,0,0,0,1,0,0,0,0,0,0,0,0,0,0,0,0,0,0,0,0,0,0,0,0,0,0,0,0,0,0,0,0,0,0,0,0,0,0,0,0,0,0,0,0,0,0,0,0,0,0,0,0,0,0,0,0,0,0,0,0,0,0,0,0,0,0],"clues":{"across":["1. Some student needs","6. ___ law","10. Weed eradicator","14. Admit wrongdoing","15. Tip","16. On the safe side","17. Memorable times","19. Geese formations","20. Title grp. in an ABC drama","21. Some Balkans","22. Popular seafood chain","26. 1950's-60's TV star","28. Cockeyed","29. \"The Odd Couple\" role","31. Reggae relative","32. Pick","35. Luau doings","37. Popular rock\/rap\/funk group","42. Deep sleep","43. Action star Steven","44. Gambling site: Abbr.","47. In 1492 it sailed the ocean blue","49. Area next to the narthex","50. False clue","52. Full of life","55. Draft holder","56. Player of one of the Corleones","57. Russian river","58. Discount coast-to-coast plane ticket","64. Shine's partner","65. Good name for a DNA expert","66. Danny of the N.B.A.","67. Ballpark amts.","68. Quaker ___","69. Mercury and Saturn"],"down":["1. Equivalent of \"ur 2 funny\"","2. Need dough","3. Household pest with a fiery appearance","4. Kook","5. Passed the buck?","6. Veteran","7. Lucille Ball, notably","8. ___ Day","9. 60's protest org.","10. Pierced body part, sometimes","11. Critical warnings","12. Nike rival","13. Corporate jet maker","18. Alternative to white","21. Wool wrap","22. Respond angrily, with \"out\"","23. Promise, for one","24. Take off quickly","25. Builder's guide","26. Atlantic fish","27. Certain greens","30. Hold aside, as a college athlete, to extend his eligibility","33. Composer who had a long relationship with George Sand","34. Easy two-pointer","36. Joe of \"Apollo 13\"","38. Like \"Lawrence of Arabia\"","39. \"Yikes!\"","40. Talk crazily","41. Go downhill","44. \"And I'm the queen of England\"","45. Popular game import from Russia","46. Robin feature","48. Puts down","51. Stirs up","53. Drink from a dish","54. A wee hour","56. Trifling amount, in a phrase","58. Teamwork disrupter","59. Pro vote","60. Secretive org.","61. Business loss","62. Geologic period","63. Article that may go with berets"]},"code":null,"copyright":"2004, The New York Times","date":"12\/30\/2004","dow":"Thursday","downmap":null,"editor":"Will Shortz","grid":["L","O","A","N","S",".","O","H","M","S",".","N","A","R","C","O","W","N","U","P",".","L","E","A","D",".","A","L","E","E","L","E","T","T","E","R","D","A","Y","S",".","V","E","E","S",".",".",".",".","N","Y","P","D",".",".","S","E","R","B","S","L","O","B","S","T","E","R",".","S","K","E","L","T","O","N","A","L","O","P",".",".","O","S","C","A","R",".","S","K","A","S","E","L","E","C","T",".","H","U","L","A","S",".",".",".","H","O","T","C","H","I","L","I","P","E","P","P","E","R","S",".",".",".","S","O","P","O","R",".","S","E","A","G","A","L","O","T","B",".","P","I","N","T","A",".",".","N","A","V","E","H","E","R","R","I","N","G",".","B","L","O","O","D","E","D","S","T","E","I","N",".",".","C","A","A","N",".",".",".",".","U","R","A","L",".","E","Y","E","S","P","E","C","I","A","L","R","I","S","E",".","G","E","N","E",".","A","I","N","G","E","E","S","T","S",".","O","A","T","S",".","M","A","K","E","S"],"gridnums":[1,2,3,4,5,0,6,7,8,9,0,10,11,12,13,14,0,0,0,0,0,15,0,0,0,0,16,0,0,0,17,0,0,0,0,18,0,0,0,0,0,19,0,0,0,0,0,0,0,20,0,0,0,0,0,21,0,0,0,0,22,23,24,25,0,0,0,0,26,27,0,0,0,0,0,28,0,0,0,0,0,29,30,0,0,0,0,31,0,0,32,0,0,0,33,34,0,35,0,0,0,36,0,0,0,37,0,0,0,0,0,38,0,0,0,0,0,39,40,41,0,0,0,42,0,0,0,0,0,43,0,0,0,0,0,44,45,46,0,47,0,0,0,48,0,0,49,0,0,0,50,0,0,51,0,0,0,0,52,53,54,0,0,0,0,55,0,0,0,0,0,0,56,0,0,0,0,0,0,0,57,0,0,0,0,58,59,0,0,0,0,60,61,62,63,64,0,0,0,0,65,0,0,0,0,66,0,0,0,0,67,0,0,0,0,68,0,0,0,0,69,0,0,0,0],"hold":null,"id":null,"id2":null,"interpretcolors":null,"jnotes":"The word RED is needed to complete LETTER DAYS, LOBSTER, SKELTON, HOT CHILI PEPPERS, HERRING, BLOODED, EYE SPECIAL, ANT, HEAD, ALERTS, SHIRT, BREAST, CENT and INK.","key":null,"mini":null,"notepad":"The three circled letters will spell a word that is missing from 14 answers in this puzzle.","publisher":"The New York Times","rbars":null,"shadecircles":null,"size":{"cols":15,"rows":15},"title":"NY TIMES, THU, DEC 30, 2004","track":null,"type":null}