{"acrossmap":null,"admin":false,"answers":{"across":["AHEAD","GPA","ASSOC","VALSE","ART","TULLY","OBELI","ZOO","RHODA","WAC","GEE","POI","WGN","INTEND","NAPOLI","NERD","SHAPE","ANOD","GROG","ERR","ETRE","AMA","CDROM","SHY","ARROW","NOFEE","ALG","ARI","TOR","USE","RUNNING","ONEMPTY","SPEEDS","BEATEN","HITS","IMAGE","FARM","ONIT","LIBRA","IKEA","TECS","KASEM","AEON"],"down":["AVOWING","HABANERA","ELECTROMAGNETIC","ASL","DEIGN","GAZE","PRO","ATOP","ATRIA","SUH","SLOWONTHEUPTAKE","OLDGLORY","CYANIDE","EDS","ONE","EDGAR","PAESE","HEDWIG","ARR","PRONTO","CORNSILK","MOONBEAM","EARSHOT","RAID","FREE","FEYNMAN","LUPINE","STEREO","NESTS","MAFIA","MIA","ABS","GRE"]},"author":"Peter A. Collins","autowrap":null,"bbars":null,"circles":[0,0,0,0,0,0,1,0,1,0,0,0,0,0,0,0,0,0,1,0,0,0,0,0,0,0,1,0,0,0,0,0,0,0,0,0,0,0,0,0,0,0,0,0,0,0,1,0,0,0,0,0,0,0,0,0,0,0,1,0,0,0,0,0,0,0,0,0,0,0,0,0,0,0,0,0,0,0,0,0,0,0,0,0,0,0,0,0,0,0,1,0,0,0,0,0,0,0,0,0,0,0,0,0,1,0,0,0,0,0,0,0,0,0,0,0,0,0,0,0,0,0,1,1,1,1,1,0,0,0,0,0,0,0,0,0,0,0,0,0,0,0,0,0,0,0,0,0,0,0,0,0,0,0,0,0,0,0,0,0,0,0,0,0,0,0,0,0,0,0,0,0,0,0,0,0,0,0,0,0,0,0,0,0,0,0,0,0,0,0,0,0,0,0,0,0,0,0,0,0,0,0,0,0,0,0,0,0,0,0,0,0,0,0,0,0,0,0,0,0,0,0,0,0,0],"clues":{"across":["1. Leading","6. Class-ranking stat","9. N.C.A.A. part: Abbr.","14. Ravel's \"La ___\"","15. Designer's major","16. Lincoln Center's Alice ___ Hall","17. Division signs","18. Chaotic scene","19. Valerie Harper title role","20. W.W. II female","21. \"No kidding!\"","23. Islands finger food","25. Chicago Cubs' station","26. Have in mind","28. Third-largest city in Italia","30. Stereotypical Mensan","31. Most athletes are in it","35. \"And giving ___, up the chimney ...\"","36. Privateer's potation","37. Boot one","38. To be, in Québec","39. Org. criticized in \"Sicko\"","40. Software package medium","42. Owing the pot","44. Direction indicator","46. Like some checking accounts","49. Typical prerequisite to geom.","51. Celebrity groom in '68 headlines","52. Blue Jays, on scoreboards","53. Put into play","55. With 57-Across, 1977 Jackson Browne album ... or a hint to what's depicted in this puzzle's grid","57. See 55-Across","59. Hightails it","60. Like eggs in omelets","61. Pete Rose's 4,256","62. Mental picture","66. Many hands may be found on it","67. Tending to the matter","68. Someone born on Columbus Day, e.g.","69. Chain that sells Borgsjö bookcases","70. P.I.'s","71. Casey with a countdown","72. \"___ Flux\" (Charlize Theron movie)"],"down":["1. Stating firmly","2. Cuban dance","3. Kind of force that affects charged particles","4. Handy way of communicating?: Abbr.","5. Lower oneself","6. Steady look","7. Moneymaker?","8. On","9. Lobbies with trees, maybe","10. Ndamukong ___, 2010 N.F.L. Defensive Rookie of the Year","11. A bit dense","12. American flag","13. Poison pill contents","22. Mag. staffers","24. Number on a foam finger","27. Musician Johnny Winter's musician brother","29. Bel ___ cheese","32. Harry Potter's owl","33. Opposite of dep.","34. On the double","40. Shucker's debris","41. Night ray","43. Eavesdropping distance","45. A bust may come of it","47. Not busy","48. 1965 Physics Nobelist Richard","50. Wolflike","54. LP introduction of 1957","56. Exterminators' targets","58. Omertà group","63. Unaccounted for, briefly","64. Six-pack ___","65. College sr.'s test"]},"code":null,"copyright":"2013, The New York Times","date":"11\/20\/2013","dow":"Wednesday","downmap":null,"editor":"Will Shortz","grid":["A","H","E","A","D",".","G","P","A",".","A","S","S","O","C","V","A","L","S","E",".","A","R","T",".","T","U","L","L","Y","O","B","E","L","I",".","Z","O","O",".","R","H","O","D","A","W","A","C",".","G","E","E",".","P","O","I",".","W","G","N","I","N","T","E","N","D",".",".",".","N","A","P","O","L","I","N","E","R","D",".","S","H","A","P","E",".","A","N","O","D","G","R","O","G",".",".","E","R","R",".",".","E","T","R","E",".","A","M","A",".","C","D","R","O","M",".","S","H","Y",".","E",".","A","R","R","O","W",".","N","O","F","E","E",".","F","A","L","G",".","A","R","I",".","T","O","R",".","U","S","E","R","U","N","N","I","N","G",".","O","N","E","M","P","T","Y","S","P","E","E","D","S",".",".",".","B","E","A","T","E","N","H","I","T","S",".","I","M","A","G","E",".","F","A","R","M","O","N","I","T",".","L","I","B","R","A",".","I","K","E","A","T","E","C","S",".","K","A","S","E","M",".","A","E","O","N"],"gridnums":[1,2,3,4,5,0,6,7,8,0,9,10,11,12,13,14,0,0,0,0,0,15,0,0,0,16,0,0,0,0,17,0,0,0,0,0,18,0,0,0,19,0,0,0,0,20,0,0,0,21,22,0,0,23,24,0,0,25,0,0,26,0,0,27,0,0,0,0,0,28,0,29,0,0,0,30,0,0,0,0,31,32,33,34,0,0,35,0,0,0,36,0,0,0,0,0,37,0,0,0,0,38,0,0,0,0,39,0,0,0,40,0,0,0,41,0,42,0,0,0,43,0,44,0,45,0,0,0,46,0,47,0,0,0,48,49,50,0,0,51,0,0,0,52,0,0,0,53,54,0,55,0,0,56,0,0,0,0,57,0,0,58,0,0,0,59,0,0,0,0,0,0,0,0,60,0,0,0,0,0,61,0,0,0,0,62,63,64,65,0,0,66,0,0,0,67,0,0,0,0,68,0,0,0,0,0,69,0,0,0,70,0,0,0,0,71,0,0,0,0,0,72,0,0,0],"hold":null,"id":null,"id2":null,"interpretcolors":null,"jnotes":null,"key":null,"mini":null,"notepad":null,"publisher":"The New York Times","rbars":null,"shadecircles":null,"size":{"cols":15,"rows":15},"title":"NY TIMES, WED, NOV 20, 2013","track":null,"type":null}