{"acrossmap":null,"admin":false,"answers":{"across":["WEBBROWSER","ITBE","OVERSTRIKE","MAUL","MILITIAMEN","SLID","ALIT","SIP","ROLLE","NENE","TETRA","YDS","SYD","BAHRAIN","HUT","EASED","SOCKHOP","HAIR","SELA","THEREOF","REMAP","ROE","CUTLASS","LED","AWL","ASHEN","ISLE","GRIFT","EVA","SOLE","LOCO","DECIPHERED","APER","AMELIORATE","NEST","HORSESENSE"],"down":["WOMANS","EVILEYE","BELINDA","BRITE","RST","OTIS","WRAITH","SIMPERS","EKE","REN","IMSO","TALLYHO","BUILDUP","ELDEST","RANKLES","TAOS","RICERS","BEARCAT","ADIEUS","SHE","HAM","ROTH","TOWROPE","HELICES","FLEECER","ALSORAN","PELLETS","RAGLAN","ANVILS","DEEDEE","ISERE","FORT","APIE","DAH","EMO","HOS"]},"author":"Rich Norris","autowrap":null,"bbars":null,"circles":null,"clues":{"across":["1. Surfing aid?","11. \"What'll ___?\" (bartender's question)","15. Superimpose","16. Trounce","17. Muster Day enrollees","18. Went down","19. Set down","20. Taste","21. Esther of \"Good Times\"","22. Madre's little one","23. Prefix with -pod","26. Passing stats: Abbr.","27. Barrett of Pink Floyd","28. Manama is its capital","30. Primitive abode","31. Made smooth","33. Quaint dance","35. Slight edge","37. 1994 Emmy-winner Ward","38. From that cause","41. Go over old ground?","44. Small deer","45. Grand Am competitor","47. Directed","49. Sewing ___","50. Terrified, perhaps","51. Guernsey, for one","52. Ill-gotten gains","54. \"Die Meistersinger\" soprano","56. Exclusive","57. Crackers","58. Figured out, in a way","61. Parrot","62. Better","63. It may be out on a limb","64. Good judgment"],"down":["1. \"A ___ Face\" (Joan Crawford film)","2. Curse","3. Actress Montgomery","4. Commercial name part meaning \"shiny\"","5. Alphabet sequence","6. Publisher Chandler","7. Apparition","8. Grins self-consciously","9. Squeeze (out)","10. One of a cartoon duo","11. \"___ Excited\" (1984 hit)","12. Hunting cry","13. Deposit","14. Tribal leaders, maybe","21. Gets to","24. D. H. Lawrence ranch site","25. Kitchen gadgets","28. Fierce fighter","29. Parting words","32. Who blows thar","34. Part of the leg","36. \"Call It Sleep\" novelist","38. Dinghy attachment, often","39. Spirals","40. Con man","42. Loser","43. Some ammunition","44. Topcoat","46. Shoemaking sites","48. One of rock's Ramones","51. Grenoble's department","53. Means of defense","55. \"...baked in ___\"","58. Long keystroke","59. First name in comedy","60. Laugh sounds"]},"code":null,"copyright":"1997, The New York Times","date":"12\/20\/1997","dow":"Saturday","downmap":null,"editor":"Will Shortz","grid":["W","E","B","B","R","O","W","S","E","R",".","I","T","B","E","O","V","E","R","S","T","R","I","K","E",".","M","A","U","L","M","I","L","I","T","I","A","M","E","N",".","S","L","I","D","A","L","I","T",".","S","I","P",".",".","R","O","L","L","E","N","E","N","E",".",".","T","E","T","R","A",".","Y","D","S","S","Y","D",".","B","A","H","R","A","I","N",".","H","U","T",".","E","A","S","E","D",".","S","O","C","K","H","O","P",".",".",".",".","H","A","I","R",".","S","E","L","A",".",".",".",".","T","H","E","R","E","O","F",".","R","E","M","A","P",".","R","O","E",".","C","U","T","L","A","S","S",".","L","E","D","A","W","L",".","A","S","H","E","N",".",".","I","S","L","E","G","R","I","F","T",".",".","E","V","A",".","S","O","L","E","L","O","C","O",".","D","E","C","I","P","H","E","R","E","D","A","P","E","R",".","A","M","E","L","I","O","R","A","T","E","N","E","S","T",".","H","O","R","S","E","S","E","N","S","E"],"gridnums":[1,2,3,4,5,6,7,8,9,10,0,11,12,13,14,15,0,0,0,0,0,0,0,0,0,0,16,0,0,0,17,0,0,0,0,0,0,0,0,0,0,18,0,0,0,19,0,0,0,0,20,0,0,0,0,21,0,0,0,0,22,0,0,0,0,0,23,0,24,25,0,0,26,0,0,27,0,0,0,28,29,0,0,0,0,0,0,30,0,0,0,31,0,32,0,0,0,33,0,0,0,34,0,0,0,0,0,0,35,0,0,36,0,37,0,0,0,0,0,0,0,38,39,0,0,0,0,40,0,41,0,0,42,43,0,44,0,0,0,45,0,0,0,46,0,0,0,47,0,48,49,0,0,0,50,0,0,0,0,0,0,51,0,0,0,52,0,0,53,0,0,0,54,0,55,0,56,0,0,0,57,0,0,0,0,58,59,0,0,0,60,0,0,0,0,61,0,0,0,0,62,0,0,0,0,0,0,0,0,0,63,0,0,0,0,64,0,0,0,0,0,0,0,0,0],"hold":null,"id":null,"id2":null,"interpretcolors":null,"jnotes":null,"key":null,"mini":null,"notepad":null,"publisher":"The New York Times","rbars":null,"shadecircles":null,"size":{"cols":15,"rows":15},"title":"NY TIMES, SAT, DEC 20, 1997","track":null,"type":null}