{"acrossmap":null,"admin":false,"answers":{"across":["AMPS","DISC","PUBS","LAIC","ANTON","INRE","ATTHEDROPOFAHAT","SHALE","EVITA","UNS","ENTREE","MARDI","KEEPYOURSHIRTON","ETE","RNS","ALA","ACCEPTS","ANYBODY","TOE","ADD","WOE","WEARINGTHEPANTS","ALDEN","ALERTS","FLU","TELAR","ATLAS","FILLEDONESSHOES","LETO","SOTTO","MART","ESSO","TAOS","AMOS"],"down":["ALAS","MATH","PITA","SCHLEP","DAD","INRERUNS","STOVERS","COPIES","PIA","UNHURT","BRANDO","SETSIN","NOT","EENY","FAMILY","TORTEN","ARAB","KEA","ETC","EEC","HANDER","ETRE","POINTE","ADHERETO","OWN","DOT","YES","ATLANTA","WAFFLE","ELLIES","ADULTS","GALOOT","PTAS","ASTHMA","EDS","LOAM","AERO","SSTS","LOO","SOS"]},"author":"A. J. Santora","autowrap":null,"bbars":null,"circles":null,"clues":{"across":["1. Intensifies, with \"up\"","5. Record","9. Sots' spots","13. Of the flock","14. Composer ___ von Webern","16. About","17. Without delay","20. Oil source","21. \"On This Night of a Thousand Stars\" musical","22. Young ___","23. It follows a starter","25. Tuesday, in Tours","27. \"Be patient!\"","31. Riviera season","32. Caregivers, for short","33. Resembling","34. Agrees to","37. \"Who has an answer?\"","41. Digital feature","42. Put on","43. Misery","44. In charge","50. Colonial John","51. They may be red","52. Runny nose cause","53. Relating to tissue","55. Trip planner's aid","59. Stepped in for another","62. Mother of Apollo","63. ___ voce (softly)","64. Gas station adjunct","65. Old station name","66. New Mexico skiing locale","67. Book after Joel"],"down":["1. \"'Tis a pity\"","2. S.A.T. part","3. Sandwich bread","4. Tote, slangily","5. \"Dear old\" guy","6. How to see \"L.A. Law\"","7. Livestock feeds","8. Knockoffs","9. ___ mater (brain cover)","10. O.K.","11. \"Viva Zapata!\" star, 1952","12. Becomes established","15. \"___ bad!\"","18. Start of a counting-out rhyme","19. G-rated","24. Rich cakes, in Germany","26. The Black Stallion, for one","27. Mauna ___","28. List abbr.","29. Common Market letters","30. Left-___ (southpaw)","35. Raison d'___","36. Grosse ___, Mich.","37. Follow","38. His or her follower","39. \"i\" lid","40. Approval","42. Turner city","44. Aren't decisive","45. Prestigious magazine awards","46. Full-price payers","47. Dumb ox","48. Fund-raising grps.","49. Bronchodilator's target","54. Wynn and others","56. Good earth","57. Prefix with gramme","58. Fast ones, for short","60. Card game with forfeits","61. \"Help!\""]},"code":null,"copyright":"2003, The New York Times","date":"10\/1\/2003","dow":"Wednesday","downmap":null,"editor":"Will Shortz","grid":["A","M","P","S",".","D","I","S","C",".",".","P","U","B","S","L","A","I","C",".","A","N","T","O","N",".","I","N","R","E","A","T","T","H","E","D","R","O","P","O","F","A","H","A","T","S","H","A","L","E",".","E","V","I","T","A",".","U","N","S",".",".",".","E","N","T","R","E","E",".","M","A","R","D","I","K","E","E","P","Y","O","U","R","S","H","I","R","T","O","N","E","T","E",".",".","R","N","S",".","A","L","A",".",".",".","A","C","C","E","P","T","S",".","A","N","Y","B","O","D","Y",".",".",".","T","O","E",".","A","D","D",".",".","W","O","E","W","E","A","R","I","N","G","T","H","E","P","A","N","T","S","A","L","D","E","N",".","A","L","E","R","T","S",".",".",".","F","L","U",".","T","E","L","A","R",".","A","T","L","A","S","F","I","L","L","E","D","O","N","E","S","S","H","O","E","S","L","E","T","O",".","S","O","T","T","O",".","M","A","R","T","E","S","S","O",".",".","T","A","O","S",".","A","M","O","S"],"gridnums":[1,2,3,4,0,5,6,7,8,0,0,9,10,11,12,13,0,0,0,0,14,0,0,0,15,0,16,0,0,0,17,0,0,0,18,0,0,0,0,0,19,0,0,0,0,20,0,0,0,0,0,21,0,0,0,0,0,22,0,0,0,0,0,23,0,24,0,0,0,0,25,26,0,0,0,27,28,29,0,0,0,0,0,0,30,0,0,0,0,0,31,0,0,0,0,32,0,0,0,33,0,0,0,0,0,34,0,0,35,36,0,0,0,37,0,0,0,38,39,40,0,0,0,41,0,0,0,42,0,0,0,0,43,0,0,44,45,46,0,0,0,47,0,0,0,48,49,0,0,0,50,0,0,0,0,0,51,0,0,0,0,0,0,0,0,52,0,0,0,53,54,0,0,0,0,55,0,56,57,58,59,0,0,60,0,0,0,0,0,61,0,0,0,0,0,62,0,0,0,0,63,0,0,0,0,0,64,0,0,0,65,0,0,0,0,0,66,0,0,0,0,67,0,0,0],"hold":null,"id":null,"id2":null,"interpretcolors":null,"jnotes":null,"key":null,"mini":null,"notepad":null,"publisher":"The New York Times","rbars":null,"shadecircles":null,"size":{"cols":15,"rows":15},"title":"NY TIMES, WED, OCT 01, 2003","track":null,"type":null}